pyTemplePriest-0.1.dist-info/METADATA
pyTemplePriest-0.1.dist-info/RECORD
pyTemplePriest-0.1.dist-info/WHEEL
pyTemplePriest-0.1.dist-info/top_level.txt
templepriest/__init__.py
templepriest/types.py
