Metadata-Version: 2.1
Name: pyTemplePriest
Version: 0.1
Summary: Python temple priest api. 
Home-page: https://github.com/painca/pyTemplePriestAPI
Author: painca
Author-email: painca@tutanota.com
License: GPL3
Platform: UNKNOWN
Requires-Dist: requests
